[{"GovernmentSecurityName":"7.10% GS 2034","Percent":6.8631000519},{"GovernmentSecurityName":"7.18% GS 2033","Percent":6.8937001228},{"GovernmentSecurityName":"7.04% GS 2029","Percent":6.7716999054},{"GovernmentSecurityName":"7.37% GS 2028","Percent":6.7820000648},{"GovernmentSecurityName":"7.02% GS 2027","Percent":6.7678999901},{"GovernmentSecurityName":"7.33% GS 2026","Percent":6.7445001602},{"GovernmentSecurityName":"91 day T-bills","Percent":6.6342000961},{"GovernmentSecurityName":"182 day T-bills","Percent":6.7210001945},{"GovernmentSecurityName":"364 day T-bills","Percent":6.7175002098}]