[{"GovernmentSecurityName":"7.18% GS 2033","Percent":7.1634001732},{"GovernmentSecurityName":"7.26% GS 2033","Percent":7.2087001801},{"GovernmentSecurityName":"7.37% GS 2028","Percent":7.0630998611},{"GovernmentSecurityName":"7.06% GS 2028","Percent":7.0728998184},{"GovernmentSecurityName":"7.33% GS 2026","Percent":7.0742001534},{"GovernmentSecurityName":"6.99% GS 2026","Percent":7.0461001396},{"GovernmentSecurityName":"91 day T-bills","Percent":6.978099823},{"GovernmentSecurityName":"182 day T-bills","Percent":7.1939001083},{"GovernmentSecurityName":"364 day T-bills","Percent":7.1898999214}]