[{"GovernmentSecurityName":"7.26% GS 2033","Percent":7.2498002052},{"GovernmentSecurityName":"7.26% GS 2032","Percent":7.266699791},{"GovernmentSecurityName":"7.06% GS 2028","Percent":7.2449002266},{"GovernmentSecurityName":"7.38% GS 2027","Percent":7.2458000183},{"GovernmentSecurityName":"6.89% GS 2025","Percent":7.1314001083},{"GovernmentSecurityName":"6.69% GS 2024","Percent":7.1616001129},{"GovernmentSecurityName":"91 day T-bills","Percent":6.8780999184},{"GovernmentSecurityName":"182 day T-bills","Percent":7.0384998322},{"GovernmentSecurityName":"364 day T-bills","Percent":7.0692000389}]