[{"GovernmentSecurityName":"7.10% GS 2034","Percent":6.9741001129},{"GovernmentSecurityName":"7.18% GS 2033","Percent":7.0304999352},{"GovernmentSecurityName":"7.04% GS 2029","Percent":6.9781999588},{"GovernmentSecurityName":"7.37% GS 2028","Percent":6.9882998466},{"GovernmentSecurityName":"7.02% GS 2027","Percent":6.9608001709},{"GovernmentSecurityName":"7.33% GS 2026","Percent":6.9611001015},{"GovernmentSecurityName":"91 day T-bills","Percent":6.8150000572},{"GovernmentSecurityName":"182 day T-bills","Percent":6.960100174},{"GovernmentSecurityName":"364 day T-bills","Percent":6.9800000191}]